{"params":[{"pid":"8cb72f44757f3ffb4d9fcd353a0af12","morenzhi":"参数","code":"cs02","beizhu":"参数02"},{"pid":"589ffe410a50789b732d12ef709e4ba","morenzhi":"0","code":"bxje","beizhu":"报销金额"},{"pid":"3e7fef49d0dfe6880421404b6223058","morenzhi":"https://api.yunkucun.top/static/ziyuan/zmlogo.png","code":"fengmian","beizhu":"封面图"}],"jiedian":[{"pid":"7de4ee124721edbb6df80193b6a4251","mingcheng":"开始节点cs","code":"kaishi","qishi":"true"},{"pid":"ba9b18bd3d6ec21a4414f1780174981","mingcheng":"过程01","code":"gc01","qishi":"false"},{"pid":"7a225ba429e38bab86fa7ee983a88c5","mingcheng":"结束","code":"jieshu","qishi":"false"},{"pid":"9af7ec7b4c25100bbda038a17b4c765","mingcheng":"过程02","code":"gc02","qishi":"false"},{"pid":"01f702584b601bd80fdda6c6bdd28b9","mingcheng":"过程03","code":"gc03","qishi":"false"},{"pid":"e339a1a13f017cf907e603b2558a7c9","mingcheng":"过程04","code":"gc04","qishi":"false"},{"pid":"7f1deb2af4962edb0b1d49363dca065","mingcheng":"过程05","code":"gc05","qishi":"false"},{"pid":"c79a293a0369081aec0969bb64acbe6","mingcheng":"测试路由（报销金额大于100）","code":"csly01","qishi":"false"},{"pid":"7895a1e79d6314cb922aec4e6e78c3f","mingcheng":"测试路由（报销金额小于100）","code":"csly02","qishi":"false"}]}